anyrun/__init__.py
anyrun/version.py
anyrun/connectors/__init__.py
anyrun/connectors/base_connector.py
anyrun/connectors/sandbox/__init__.py
anyrun/connectors/sandbox/base_connector.py
anyrun/connectors/sandbox/sandbox_connectors_fabric.py
anyrun/connectors/sandbox/operation_systems/__init__.py
anyrun/connectors/sandbox/operation_systems/android.py
anyrun/connectors/sandbox/operation_systems/linux.py
anyrun/connectors/sandbox/operation_systems/windows.py
anyrun/connectors/threat_intelligence/__init__.py
anyrun/connectors/threat_intelligence/feeds_connector.py
anyrun/connectors/threat_intelligence/lookup_connector.py
anyrun/connectors/threat_intelligence/yara_lookup_connector.py
anyrun/iterators/__init__.py
anyrun/iterators/base_iterator.py
anyrun/iterators/threat_intelligence/__init__.py
anyrun/iterators/threat_intelligence/feeds/__init__.py
anyrun/iterators/threat_intelligence/feeds/feeds_iterators_fabric.py
anyrun/iterators/threat_intelligence/feeds/taxii_stix_iterator.py
anyrun/iterators/threat_intelligence/yara_lookup/__init__.py
anyrun/iterators/threat_intelligence/yara_lookup/json_iterator.py
anyrun/iterators/threat_intelligence/yara_lookup/stix_iterator.py
anyrun/iterators/threat_intelligence/yara_lookup/yara_lookup_iterators_fabric.py
anyrun/utils/__init__.py
anyrun/utils/config.py
anyrun/utils/exceptions.py
anyrun/utils/utility_functions.py
anyrun_sdk-1.12.11.dist-info/licenses/LICENSE
anyrun_sdk-1.12.11.dist-info/METADATA
anyrun_sdk-1.12.11.dist-info/WHEEL
anyrun_sdk-1.12.11.dist-info/top_level.txt
anyrun_sdk-1.12.11.dist-info/RECORD
