Metadata-Version: 2.4
Name: anyrun-sdk
Version: 1.12.11
Summary: This is the official Python client library for ANY.RUN. Automate management of ANY.RUN REST endpoints
Author-email: Semen Shalnev <support@any.run>
License: Apache v2.0
Project-URL: Homepage, https://github.com/anyrun/anyrun-sdk
Project-URL: Examples, https://github.com/anyrun/anyrun-sdk/tree/main/examples
Classifier: Programming Language :: Python :: 3.9
Classifier: Programming Language :: Python :: 3.10
Classifier: Programming Language :: Python :: 3.11
Classifier: Programming Language :: Python :: 3.12
Classifier: Programming Language :: Python :: 3.13
Classifier: Topic :: Software Development :: Libraries
Classifier: Typing :: Typed
Requires-Python: >=3.9
License-File: LICENSE
Requires-Dist: aiohttp>=3.12.14
Requires-Dist: aiofiles>=24.1.0
Requires-Dist: typing-extensions>=4.12.2
Requires-Dist: requests>=2.32.4
Provides-Extra: dev
Requires-Dist: pytest==8.3.4; extra == "dev"
Requires-Dist: pytest-asyncio==0.25.3; extra == "dev"
Requires-Dist: pytest-cov==6.0.0; extra == "dev"
Dynamic: license-file
